circleml/__init__.py
circleml/core/__init__.py
circleml/core/base/__init__.py
circleml/core/base/abcs.py
circleml/core/math/__init__.py
circleml/core/math/math.py
circleml/knn/__init__.py
circleml/knn/knn.py
circleml/log/__init__.py
circleml/log/logger.py
circleml-0.0.1.dist-info/LICENSE
circleml-0.0.1.dist-info/METADATA
circleml-0.0.1.dist-info/WHEEL
circleml-0.0.1.dist-info/top_level.txt
circleml-0.0.1.dist-info/RECORD
