Metadata-Version: 2.1
Name: circleml
Version: 0.0.1
Summary: A machine learning library for Python.
Author-email: SamTheProgrammer <user@example.com>
Project-URL: Homepage, https://github.com/tetrahedronai/circle
Project-URL: Bug Tracker, https://github.com/tetrahedronai/circle/issues
Classifier: Programming Language :: Python :: 3
Classifier: License :: OSI Approved :: MIT License
Classifier: Operating System :: OS Independent
Requires-Python: >=3.7
License-File: LICENSE
